{
  "https://www.ss.com/msg/lv/transport/cars/tesla/model-s/cgcbme.html": "2026-04-10T16:24:27.528616",
  "https://www.ss.com/msg/lv/transport/cars/tesla/model-y/cgfxdh.html": "2026-04-10T16:24:27.528616",
  "https://www.ss.com/msg/lv/transport/cars/tesla/model-3/cfpeoe.html": "2026-04-10T16:24:27.528616",
  "https://www.ss.com/msg/lv/transport/cars/tesla/model-s/cgboim.html": "2026-04-10T16:24:27.528616",
  "https://www.ss.com/msg/lv/transport/cars/tesla/model-y/cgddmi.html": "2026-04-10T16:24:27.528616",
  "https://www.ss.com/msg/lv/transport/cars/tesla/model-3/cgbxig.html": "2026-04-10T16:24:27.528616",
  "https://www.ss.com/msg/lv/transport/cars/tesla/model-3/cgxexb.html": "2026-04-10T16:24:27.528616",
  "https://www.ss.com/msg/lv/transport/cars/tesla/model-3/cgxemg.html": "2026-04-10T16:24:27.528616",
  "https://www.ss.com/msg/lv/transport/cars/tesla/model-3/cfmdkf.html": "2026-04-10T16:24:27.528616",
  "https://www.ss.com/msg/lv/transport/cars/tesla/model-y/cfnefp.html": "2026-04-10T16:24:27.528616",
  "https://www.dba.dk/mobility/item/20393763": "2026-04-10T16:24:27.528616",
  "https://www.dba.dk/mobility/item/20392408": "2026-04-10T16:24:27.528616",
  "https://www.dba.dk/mobility/item/20389135": "2026-04-10T16:24:27.528616",
  "https://www.dba.dk/mobility/item/20387194": "2026-04-10T16:24:27.528616",
  "https://www.dba.dk/mobility/item/20386955": "2026-04-10T16:24:27.528616",
  "https://www.dba.dk/mobility/item/20382945": "2026-04-10T16:24:27.528616",
  "https://www.dba.dk/mobility/item/20381981": "2026-04-10T16:24:27.528616",
  "https://www.dba.dk/mobility/item/20381074": "2026-04-10T16:24:27.528616",
  "https://www.dba.dk/mobility/item/20366637": "2026-04-10T16:24:27.528616",
  "https://www.dba.dk/mobility/item/20363642": "2026-04-10T16:24:27.528616",
  "https://www.dba.dk/mobility/item/20359741": "2026-04-10T16:24:27.528616",
  "https://www.dba.dk/mobility/item/20353845": "2026-04-10T16:24:27.528616",
  "https://www.dba.dk/mobility/item/20262275": "2026-04-10T16:24:27.528616",
  "https://www.dba.dk/mobility/item/20346396": "2026-04-10T16:24:27.528616",
  "https://www.dba.dk/mobility/item/20339791": "2026-04-10T16:24:27.528616",
  "https://www.dba.dk/mobility/item/20335321": "2026-04-10T16:24:27.528616",
  "https://www.dba.dk/mobility/item/20319155": "2026-04-10T16:24:27.528616",
  "https://www.dba.dk/mobility/item/20307570": "2026-04-10T16:24:27.528616",
  "https://www.dba.dk/mobility/item/20303197": "2026-04-10T16:24:27.528616",
  "https://www.dba.dk/mobility/item/20302366": "2026-04-10T16:24:27.528616",
  "https://www.dba.dk/mobility/item/20301507": "2026-04-10T16:24:27.528616",
  "https://www.dba.dk/mobility/item/20277251": "2026-04-10T16:24:27.528616",
  "https://www.dba.dk/mobility/item/20271662": "2026-04-10T16:24:27.528616",
  "https://www.dba.dk/mobility/item/20266225": "2026-04-10T16:24:27.528616",
  "https://www.dba.dk/mobility/item/20179417": "2026-04-10T16:24:27.528616",
  "https://www.dba.dk/mobility/item/20105765": "2026-04-10T16:24:27.528616",
  "https://www.dba.dk/mobility/item/20100886": "2026-04-10T16:24:27.528616",
  "https://www.dba.dk/mobility/item/20098722": "2026-04-10T16:24:27.528616",
  "https://www.dba.dk/mobility/item/18123197": "2026-04-10T16:24:27.528616",
  "https://www.dba.dk/mobility/item/20070142": "2026-04-10T16:24:27.528616",
  "https://www.dba.dk/mobility/item/20069681": "2026-04-10T16:24:27.528616",
  "https://www.dba.dk/mobility/item/20066332": "2026-04-10T16:24:27.528616",
  "https://www.dba.dk/mobility/item/20065256": "2026-04-10T16:24:27.528616",
  "https://www.dba.dk/mobility/item/20060333": "2026-04-10T16:24:27.528616",
  "https://www.dba.dk/mobility/item/20055340": "2026-04-10T16:24:27.528616",
  "https://www.dba.dk/mobility/item/16096783": "2026-04-10T16:24:27.528616",
  "https://www.dba.dk/mobility/item/15741499": "2026-04-10T16:24:27.528616",
  "https://www.dba.dk/mobility/item/19997886": "2026-04-10T16:24:27.528616",
  "https://www.dba.dk/mobility/item/19994391": "2026-04-10T16:24:27.528616",
  "https://www.dba.dk/mobility/item/19989644": "2026-04-10T16:24:27.528616",
  "https://www.dba.dk/mobility/item/19989643": "2026-04-10T16:24:27.528616",
  "https://www.dba.dk/mobility/item/19961618": "2026-04-10T16:24:27.528616",
  "https://www.dba.dk/mobility/item/19937611": "2026-04-10T16:24:27.528616",
  "https://www.dba.dk/mobility/item/19936248": "2026-04-10T16:24:27.528616",
  "https://www.dba.dk/mobility/item/19908529": "2026-04-10T16:24:27.528616",
  "https://www.dba.dk/mobility/item/19899379": "2026-04-10T16:24:27.528616",
  "https://www.dba.dk/mobility/item/19890028": "2026-04-10T16:24:27.528616",
  "https://www.dba.dk/mobility/item/19873528": "2026-04-10T16:24:27.528616",
  "https://www.dba.dk/mobility/item/19871872": "2026-04-10T16:24:27.528616",
  "https://www.ss.com/msg/lv/transport/cars/tesla/model-s/cgknnn.html": "2026-04-10T17:12:22.547341",
  "https://www.dba.dk/mobility/item/19699042": "2026-04-10T23:01:32.703270",
  "https://www.dba.dk/mobility/item/20328325": "2026-04-10T23:01:32.703270",
  "https://www.dba.dk/mobility/item/19895645": "2026-04-10T23:01:32.703270",
  "https://www.ss.com/msg/lv/transport/cars/tesla/model-s/cfohjg.html": "2026-04-11T05:16:16.050009",
  "https://www.ss.com/msg/lv/transport/cars/tesla/model-3/cfnbno.html": "2026-04-11T14:03:00.909950"
}